odoo/addons/account_invoice_discount_date/README.rst
odoo/addons/account_invoice_discount_date/__init__.py
odoo/addons/account_invoice_discount_date/__manifest__.py
odoo/addons/account_invoice_discount_date/i18n/account_invoice_discount_date.pot
odoo/addons/account_invoice_discount_date/i18n/es.po
odoo/addons/account_invoice_discount_date/i18n/it.po
odoo/addons/account_invoice_discount_date/models/__init__.py
odoo/addons/account_invoice_discount_date/models/account_move.py
odoo/addons/account_invoice_discount_date/readme/CONTEXT.md
odoo/addons/account_invoice_discount_date/readme/CONTRIBUTORS.md
odoo/addons/account_invoice_discount_date/readme/DESCRIPTION.md
odoo/addons/account_invoice_discount_date/readme/USAGE.md
odoo/addons/account_invoice_discount_date/static/description/icon.png
odoo/addons/account_invoice_discount_date/static/description/index.html
odoo/addons/account_invoice_discount_date/tests/__init__.py
odoo/addons/account_invoice_discount_date/tests/test_account_invoice_discount_date.py
odoo/addons/account_invoice_discount_date/views/account_move_line_view.xml
odoo/addons/account_invoice_discount_date/views/account_move_view.xml
odoo_addon_account_invoice_discount_date-16.0.1.0.1.2.dist-info/METADATA
odoo_addon_account_invoice_discount_date-16.0.1.0.1.2.dist-info/WHEEL
odoo_addon_account_invoice_discount_date-16.0.1.0.1.2.dist-info/top_level.txt
odoo_addon_account_invoice_discount_date-16.0.1.0.1.2.dist-info/RECORD
